AUTHORS.rst
CONTRIBUTING.rst
HISTORY.rst
MANIFEST.in
README.rst
setup.py
docs/Makefile
docs/authors.rst
docs/conf.py
docs/contributing.rst
docs/history.rst
docs/index.rst
docs/installation.rst
docs/make.bat
docs/readme.rst
docs/usage.rst
osm_road_length/__init__.py
osm_road_length/osm_road_length.py
osm_road_length.egg-info/PKG-INFO
osm_road_length.egg-info/SOURCES.txt
osm_road_length.egg-info/dependency_links.txt
osm_road_length.egg-info/not-zip-safe
osm_road_length.egg-info/requires.txt
osm_road_length.egg-info/top_level.txt
tests/__init__.py
tests/test_osm_road_length.py