Metadata-Version: 1.2
Name: osm-road-length
Version: 0.1.5
Summary: Calculate Open Street Maps road length for any polygon
Home-page: https://github.com/JoaoCarabetta/osm-road-length
Author: Joao Carabetta
Author-email: joao.carabetta@gmail.com
License: MIT license
Platform: UNKNOWN
Classifier: Development Status :: 2 - Pre-Alpha
Classifier: Intended Audience :: Developers
Classifier: License :: OSI Approved :: MIT License
Classifier: Natural Language :: English
Classifier: Programming Language :: Python :: 3
Requires-Python: >=3
